{"conStartDate":"2020-07-12","registrationOpenDate":"2020-02-06T09:59","registrationCloseDate":"2020-06-07T00:00","volunteerRegistrationOpenDate":"2020-02-05T15:00","numberOfInsideSpots":"6","numberOfOutsideSpots":4,"originalPaymentDeadline":"2020-06-23T23:59","finalPaymentDeadline":"2021-06-29T23:59","isSellingHoodies":true,"isSellingTshirts":true,"mainDaysInsidePriceNok":1099,"mainDaysOutsidePriceNok":1001,"earlyArrivalPriceNok":300,"lateDeparturePriceNok":300,"singeDayTicketPriceNok":350,"hoodiePriceNok":500,"tshirtPriceNok":250}